{
"type": "FeatureCollection",
"name": "Homepoint",
"crs": { "type": "name", "properties": { "name": "urn:ogc:def:crs:OGC:1.3:CRS84" } },
"features": [
{ "type": "Feature", "properties": { "id": null }, "geometry": { "type": "Point", "coordinates": [ -80.788599401812064, 35.175174840793062 ] } }
]
}
